{
  "plugins": {
    "blink.cmp": {
      "rev": "a4ab037",
      "src": "https://github.com/Saghen/blink.cmp"
    },
    "nvim-lspconfig": {
      "rev": "ac98db2",
      "src": "https://github.com/neovim/nvim-lspconfig"
    },
    "nvim-treesitter": {
      "rev": "42fc28ba",
      "src": "https://github.com/nvim-treesitter/nvim-treesitter",
      "version": "'master'"
    },
    "oil.nvim": {
      "rev": "7194872",
      "src": "https://github.com/stevearc/oil.nvim"
    },
    "plenary.nvim": {
      "rev": "b9fd522",
      "src": "https://github.com/nvim-lua/plenary.nvim"
    },
    "replua.nvim": {
      "rev": "8084695",
      "src": "https://github.com/mghaight/replua.nvim"
    },
    "telescope.nvim": {
      "rev": "b4da76b",
      "src": "https://github.com/nvim-telescope/telescope.nvim"
    },
    "typst-preview.nvim": {
      "rev": "1603d37",
      "src": "https://github.com/chomosuke/typst-preview.nvim"
    }
  }
}